<SplineRoad>
	<mtr river="0" road="roadJungle" pipe="pipeAsphalt" pipe2="pipeGlass" wall="road_wall_Jungle" pipeW="pipe_wall_Jungle" col="road_col_Dark" />
	<dim tcMul="0.0404529" tcW="0.2" tcP="0.1" tcPW="0.3" tcC="0.2" lenDim="2" widthSteps="6" heightOfs="0.06" />
	<mrg loop="1" skirtLen="1" skirtH="0.12" merge="1" mergeLen="1200" lodPntLen="120" visDist="1000" visBehind="800" />
	<geom colN="4" colR="2" wsPm="4" lsPm="1" stBox="1 5 21.8241" iDir="1" iChk1="54" />
	<stats length="5947.08" width="11.5313" height="131.699" onTer="4.01701" pipes="0" bnkAvg="4.60127" bnkMax="20.0367" />
	<txt desc="Majestic and rather empty jungle scenery." />
	<adv ice="Terrain with high slopes and few jumps, but has fast driving in lower parts. With one narrow hill climb." />
	<P pos="167.653 0 -359.019" w="6" aT="2" chkR="7.14" />
	<P pos="173.975 0 -504.051" w="6" aT="2" />
	<P pos="258.565 0 -555.142" w="6" aT="2" chkR="5.668" />
	<P pos="281.908 0 -565.632" w="6" aT="2" />
	<P pos="304.509 0 -574.914" w="6" aT="2" />
	<P pos="326.704 0 -587.587" w="6.5196" a="127.62" ar="0" aT="0" />
	<P pos="340.07 46.5387 -612.881" w="6.5196" onTer="0" a="127.62" ar="1.02" aT="1" />
	<P pos="347.098 46.5291 -643.299" w="6.5196" onTer="0" a="-180.78" ar="3.48" aT="1" col="0" />
	<P pos="357.166 46.5281 -699.683" w="6.5196" onTer="0" a="-187.02" ar="0.539997" aT="0" col="0" />
	<P pos="366.521 46.5631 -753.103" w="6.5196" onTer="0" a="-187.02" ar="0.539997" aT="1" />
	<P pos="372.07 46.5571 -781.116" w="6.5196" onTer="0" a="-187.02" ar="0.539997" aT="1" />
	<P pos="378.806 46.6841 -800.152" w="6.5196" onTer="0" a="-187.02" ar="0.539997" aT="1" />
	<P pos="392.643 0 -811.963" w="6.5196" a="121.32" ar="0" aT="1" />
	<P pos="423.627 0 -824.201" w="6" aT="2" chkR="3.064" />
	<P pos="449.694 0 -841.592" w="6" aT="2" />
	<P pos="467.752 0 -855.69" w="6" aT="2" />
	<P pos="484.395 0 -869.177" w="6" aT="2" />
	<P pos="497.116 0 -879.333" w="6" aT="2" />
	<P pos="507.171 0 -886.039" w="6" aT="2" />
	<P pos="512.541 0 -884.585" w="6" aT="2" chkR="5.04" />
	<P pos="506.85 0 -873.698" w="6" aT="2" />
	<P pos="498.879 0 -862.64" w="6" aT="2" />
	<P pos="487.367 0 -846.578" w="6" aT="2" />
	<P pos="469.02 0 -822.501" w="6" aT="2" />
	<P pos="454.347 0 -801.511" w="6" aT="2" />
	<P pos="453.626 0 -791.382" w="6" aT="2" chkR="6.84" />
	<P pos="461.93 0 -791.446" w="6" aT="2" />
	<P pos="474.306 0 -803.655" w="6" aT="2" />
	<P pos="490.08 0 -822.484" w="6" aT="2" />
	<P pos="503.811 0 -838.319" w="6" aT="2" />
	<P pos="529.378 0 -850.6" w="6" aT="2" chkR="6.56" />
	<P pos="564.595 0 -780.138" w="6" aT="2" chkR="6.568" />
	<P pos="449.334 0 -705.439" w="15.48" aT="2" />
	<P pos="241.949 0 -715.027" w="15.72" aT="2" chkR="3.796" />
	<P pos="82.2468 0 -625.391" w="15.176" aT="2" />
	<P pos="-109.805 0 -333.172" w="15.096" aT="2" />
	<P pos="-235.179 0 -250.419" w="15.776" aT="2" chkR="3.02" />
	<P pos="-358.387 0 -208.188" w="15.832" aT="2" />
	<P pos="-520.487 0 -83.395" w="9.848" aT="2" />
	<P pos="-567.093 0 172.763" w="11.168" aT="2" chkR="4.16" />
	<P pos="-504.065 0 302.661" w="10.376" aT="2" />
	<P pos="-370.876 0 359.243" w="9.768" aT="2" chkR="3.624" />
	<P pos="-322.376 0 421.602" w="6" aT="2" />
	<P pos="-270.835 0 520.539" w="10.128" aT="2" />
	<P pos="-262.212 0 663.776" w="9.72" aT="2" />
	<P pos="-219.365 0 789.54" w="10.016" aT="2" />
	<P pos="-149.81 0 833.769" w="8.856" aT="2" chkR="4.136" />
	<P pos="-91.3278 0 817.37" w="8.272" aT="2" />
	<P pos="-63.5129 0 798.156" w="8.344" aT="2" />
	<P pos="25.9871 0 722.094" w="9.456" aT="2" chkR="3.672" />
	<P pos="188.91 0 761.223" w="9.192" aT="2" chkR="3.876" />
	<P pos="275.79 0 753.397" w="6" aT="2" />
	<P pos="356.765 0 738.041" w="20.728" aT="2" />
	<P pos="431.135 0 691.667" w="20.48" aT="2" />
	<P pos="702.606 0 466.521" w="6" aT="2" chkR="3.188" />
	<P pos="847.321 0 417.404" w="6" aT="2" />
	<P pos="866.877 0 335.572" w="6" aT="2" chkR="4.92" />
	<P pos="839.061 0 268.318" w="15.12" aT="2" />
	<P pos="780.68 0 181.658" w="14.8" aT="2" />
	<P pos="679.322 0 110.375" w="14.824" aT="2" />
	<P pos="576.303 0 -32.5831" w="14.952" aT="2" chkR="3.452" />
	<P pos="403.188 0 -2.80322" w="14.008" aT="2" />
	<P pos="277.03 0 -126.69" w="14.224" aT="2" chkR="2.352" />
</SplineRoad>
