<scene>
	<car tires="0" />
	<start pos="-339.986 -235.565 1.83783" rot="-0.04219 0.03653 -0.641465 0.765127" />
	<sound ambient="" reverbs="Rocky" />
	<sky material="sky/morning_gen" />
	<fog color="0.83 0.62 0.45 0.9" color2="0.73 0.63 0.53 0.9" linStart="402.523" linEnd="970.898" />
	<fogH color="0.3 0.24 0.2 0.95" height="-1.785" dens="20.1612" linStart="0" linEnd="0.2" />
	<light pitch="40.1504" yaw="-8" ambient="0.5 0.5 0.5" diffuse="1 1 1" specular="0.7 0.7 0.7" />
	<fluids>
		<fluid name="mud hard" pos="-149.195 -21.9303 144.915" rot="0 0 0" size="318.331 40 299.27" tile="0.01 0.01" />
	</fluids>
	<terrain size="1025" triangle="1.11854" errNorm="10.00">
		<texture on="1" file="adesert_sand2_d.jpg" fnorm="desert_sand2_n.jpg" scale="8.5" surf="DesertFast" dust="0.7" dustS="1" mud="0.4" smoke="0" tclr="0.46 0.26 0.08 0.7" angMin="0" angMax="20.4305" angSm="11.3931" hMin="-300" hMax="300" hSm="20" nOn="0" noise="1" n_1="0" n2="0">
			<noise frq0="17.2152" oct0="4" prs0="0.49" pow0="1.9" frq1="8.6994" oct1="3" prs1="0.461644" pow1="2.97877" />
		</texture>
		<texture on="1" file="adesert_rocky_d.jpg" fnorm="desert_rocky_n.jpg" scale="18.0217" surf="DesertFast" dust="0.6" dustS="1" mud="0.5" smoke="0" tclr="0.48 0.3 0.2 0.8" angMin="21.7448" angMax="42.6844" angSm="9.89247" hMin="-300" hMax="300" hSm="20" nOn="0" noise="0.496644" n_1="0" n2="0">
			<noise frq0="26.2" oct0="3" prs0="0.3" pow0="1.5" frq1="31.5" oct1="3" prs1="0.4" pow1="1.2" />
		</texture>
		<texture on="1" file="adesert_mntn_d.jpg" fnorm="desert_mntn_n.jpg" scale="40.8113" surf="DesertFast" dust="0" dustS="0.2" mud="1" smoke="0" tclr="0.2 0.2 0 1" angMin="45.1006" angMax="90" angSm="27.9865" hMin="-300" hMax="300" hSm="20" nOn="0" triplanar="1" noise="0.111856" n_1="0" n2="0">
			<noise frq0="30.2" oct0="3" prs0="0.3" pow0="1.5" frq1="34.5" oct1="3" prs1="0.4" pow1="1.2" />
		</texture>
		<texture on="0" file="" fnorm="" scale="14.1" surf="Default" dust="0.8" dustS="1" mud="0.4" smoke="0" tclr="0.48 0.26 0.08 0.7" angMin="54.5637" angMax="90" angSm="20" hMin="-300" hMax="300" hSm="20" nOn="0" noise="1" n_1="0" n2="0">
			<noise frq0="34.2" oct0="3" prs0="0.3" pow0="1.5" frq1="37.5" oct1="3" prs1="0.4" pow1="1.2" />
		</texture>
		<texture on="0" file="" fnorm="" scale="10.4" surf="Default" dust="0.5" dustS="1" mud="0.5" smoke="0" tclr="0.42 0.26 0.08 0.8" angMin="0" angMax="90" angSm="20" hMin="-300" hMax="300" hSm="20" nOn="0" noise="1" n_1="0" n2="0">
			<noise frq0="38.2" oct0="3" prs0="0.3" pow0="1.5" frq1="40.5" oct1="3" prs1="0.4" pow1="1.2" />
		</texture>
		<texture on="0" file="" fnorm="" scale="4.5" surf="Default" dust="0" dustS="0.2" mud="1" smoke="0" tclr="0.2 0.2 0 1" angMin="0" angMax="90" angSm="20" hMin="-300" hMax="300" hSm="20" nOn="0" noise="1" n_1="0" n2="0">
			<noise frq0="42.2" oct0="3" prs0="0.3" pow0="1.5" frq1="43.5" oct1="3" prs1="0.4" pow1="1.2" />
		</texture>
		<texture road="1" surf="roadAdesert" dust="0.5" dustS="0.6" mud="0" smoke="0" tclr="0.54 0.3 0.22 0.7" />
		<par dust="Adust" mud="Mud" smoke="Smoke" />
	</terrain>
	<paged densGrass="0.06" densTrees="2.5" grPage="100" grDist="100" grDensSmooth="2" trPage="120" trDist="120" trDistImp="600" trRdDist="2">
		<grass on="1" mtr="grass6s" clr="grClrWinter.png" dens="0.201138" chan="0" minSx="1.48959" maxSx="1.75063" minSy="1.39749" maxSy="1.75063" swayDistr="4" swayLen="0.2" swaySpeed="0.5" />
		<grass on="0" mtr="grass16r" clr="grClrWinter.png" dens="0.141625" chan="0" minSx="1.99746" maxSx="2.3799" minSy="1.56875" maxSy="1.92518" swayDistr="4" swayLen="0.2" swaySpeed="0.5" />
		<grass on="1" mtr="grass17r" clr="grClrJungle.png" dens="0.244464" chan="0" minSx="1.55274" maxSx="1.73366" minSy="1.0868" maxSy="1.251" swayDistr="4" swayLen="0.2" swaySpeed="0.5" />
		<grass on="1" mtr="grass12o" clr="grClrAustralia.png" dens="0.235885" chan="0" minSx="1.39749" maxSx="1.76769" minSy="1.18105" maxSy="1.58485" swayDistr="4" swayLen="0.2" swaySpeed="0.5" />
		<grass on="1" mtr="grass10" clr="grClrJungle.png" dens="0.0462495" chan="0" minSx="1.58485" maxSx="1.92518" minSy="1.30854" maxSy="1.55274" swayDistr="4" swayLen="0.2" swaySpeed="0.5" />
		<grass on="1" mtr="grass20" clr="grClrJungle.png" dens="0.1" chan="0" minSx="1.42784" maxSx="1.60103" minSy="2.14623" maxSy="2.50147" swayDistr="4" swayLen="0.2" swaySpeed="0.5" />
		<gchan amin="0" amax="5" asm="3" hmin="-10" hmax="44" hsm="10" ns="0" frq="25" oct="3" prs="0.3" pow="1.2" rd="0" />
		<gchan amin="0" amax="30" asm="20" hmin="-100" hmax="100" hsm="20" ns="0" frq="31" oct="3" prs="0.3" pow="1.2" rd="0" />
		<gchan amin="0" amax="30" asm="20" hmin="-100" hmax="100" hsm="20" ns="0" frq="37" oct="3" prs="0.3" pow="1.2" rd="0" />
		<gchan amin="0" amax="30" asm="20" hmin="-100" hmax="100" hsm="20" ns="0" frq="43" oct="3" prs="0.3" pow="1.2" rd="0" />
		<layer on="1" name="gum_tree.mesh" dens="0.138355" minScale="0.339999" maxScale="1.14" ofsY="0" addTrRdDist="2" maxRdist="100" windFx="0.799993" windFy="0.0139993" maxTerAng="14.3369" minTerH="-1" maxTerH="1" maxDepth="0" />
		<layer on="1" name="tree.07.mesh" dens="0.0453213" minScale="0.447879" maxScale="0.67379" ofsY="0" addTrRdDist="2" maxRdist="100" windFx="0.699996" windFy="0.00999977" maxTerAng="11.6413" minTerH="-1" maxTerH="1" maxDepth="0" />
		<layer on="0" name="tree.09.mesh" dens="0.00758376" minScale="0.849996" maxScale="1.15" ofsY="0" addTrRdDist="2" maxRdist="100" windFx="0.599999" windFy="0.00999978" maxTerAng="10.132" minTerH="-1" maxTerH="1" maxDepth="0" />
		<layer on="1" name="treeD-22desMed.mesh" dens="0.0570942" minScale="1.07413" maxScale="1.62451" ofsY="0" addTrRdDist="0" maxRdist="100" windFx="0.271679" windFy="0.0115325" maxTerAng="24.517" minTerH="-2" maxTerH="2" maxDepth="0" />
		<layer on="1" name="treeGC-32draUp.mesh" dens="0.0199999" minScale="1.03695" maxScale="1.4959" ofsY="0" addTrRdDist="0" maxRdist="100" windFx="0.229809" windFy="0.0148893" maxTerAng="24.3114" minTerH="-2" maxTerH="2" maxDepth="0" />
		<layer on="1" name="rock.05.mesh" dens="0.0116235" minScale="0.0599978" maxScale="0.409999" ofsY="0" addTrRdDist="3" maxRdist="100" windFx="0" windFy="0" maxTerAng="22.3031" minTerH="-33" maxTerH="5" maxDepth="1" />
		<layer on="0" name="rock.07.mesh" dens="0.0199999" minScale="0.0599979" maxScale="0.409999" ofsY="0" addTrRdDist="3" maxRdist="100" windFx="0" windFy="0" maxTerAng="38.1791" minTerH="-10" maxTerH="10" maxDepth="1" />
		<layer on="1" name="treeD-34desTiny.mesh" dens="0.059191" minScale="1.01265" maxScale="1.4959" ofsY="0" addTrRdDist="0" maxRdist="100" windFx="0.271679" windFy="0.0107806" maxTerAng="20.7587" minTerH="10" maxTerH="33" maxDepth="0" />
		<layer on="0" name="" dens="0.0999996" minScale="0.0999994" maxScale="0.249999" ofsY="0" addTrRdDist="0" maxRdist="100" windFx="0" windFy="0" maxTerAng="50" minTerH="-100" maxTerH="100" maxDepth="5" />
		<layer on="0" name="" dens="0.1" minScale="0.1" maxScale="0.25" ofsY="0" addTrRdDist="0" maxRdist="100" windFx="0" windFy="0" maxTerAng="50" minTerH="-100" maxTerH="100" maxDepth="5" />
	</paged>
	<cam pos="-190.48 113.254 -570.491" dir="0.307863 -0.218448 0.926013" />
	<objects />
</scene>
