<scene>
	<car tires="0" />
	<start pos="-124.829 46.1881 7.19351" rot="-0.012406 0.012689 -0.846215 -0.532561" />
	<sound ambient="" reverbs="Savanna" />
	<sky material="sky/day_blue2" />
	<fog color="0.52 0.6 0.66 1" color2="0.55 0.69 0.77 1" linStart="82.875" linEnd="576.504" />
	<fogH color="0.57 0.58 0.59 1" height="0" dens="59.405" linStart="0" linEnd="88.2" />
	<light pitch="33.1752" yaw="45" ambient="0.55 0.55 0.55" diffuse="0.8 0.8 0.8" specular="0.5 0.5 0.5" />
	<fluids />
	<terrain size="513" triangle="0.820047" errNorm="5.00">
		<texture on="1" file="grass_green2y_d.jpg" fnorm="grass_green2y_n.jpg" scale="12.3214" surf="GrassForest" dust="0" dustS="0.2" mud="0.8" smoke="0" tclr="0.22 0.2 0.04 0.9" angMin="0" angMax="16.3796" angSm="6.40863" hMin="-300" hMax="300" hSm="20" nOn="0" noise="1" n_1="0" n2="1">
			<noise frq0="33.7041" oct0="3" prs0="0.3" pow0="0.810836" frq1="41.0417" oct1="3" prs1="0.576712" pow1="5.22135" />
		</texture>
		<texture on="1" file="grass_ground_d.jpg" fnorm="grass_ground_n.jpg" scale="7.1582" surf="GrassForest" dust="0" dustS="0.2" mud="0.6" smoke="0" tclr="0.32 0.31 0.08 0.9" angMin="17.9648" angMax="31.1742" angSm="5.77764" hMin="-300" hMax="300" hSm="20" nOn="0" noise="1" n_1="0" n2="0">
			<noise frq0="26.2" oct0="3" prs0="0.3" pow0="1.5" frq1="31.5" oct1="3" prs1="0.4" pow1="1.2" />
		</texture>
		<texture on="1" file="grass_rocky_d.jpg" fnorm="grass_rocky_n.jpg" scale="8.30655" surf="GrassForest" dust="0" dustS="0.2" mud="1" smoke="0" tclr="0.2 0.2 0 1" angMin="33.2877" angMax="42.2701" angSm="9.4158" hMin="-300" hMax="300" hSm="20" nOn="0" noise="0" n_1="0" n2="0">
			<noise frq0="30.2" oct0="3" prs0="0.3" pow0="1.5" frq1="34.5" oct1="3" prs1="0.4" pow1="1.2" />
		</texture>
		<texture on="1" file="mntn_gray_d.jpg" fnorm="mntn_dark_n.jpg" scale="27.9749" surf="Rocks" dust="0" dustS="0.2" mud="1" smoke="0" tclr="0.2 0.2 0 1" angMin="36.9863" angMax="90" angSm="14.5167" hMin="-300" hMax="300" hSm="20" nOn="0" noise="1" n_1="0" n2="0">
			<noise frq0="34.2" oct0="3" prs0="0.3" pow0="1.5" frq1="37.5" oct1="3" prs1="0.4" pow1="1.2" />
		</texture>
		<texture on="0" file="" fnorm="" scale="4.5" surf="Default" dust="0" dustS="0.2" mud="1" smoke="0" tclr="0.2 0.2 0 1" angMin="0" angMax="90" angSm="20" hMin="-300" hMax="300" hSm="20" nOn="0" noise="1" n_1="0" n2="0">
			<noise frq0="38.2" oct0="3" prs0="0.3" pow0="1.5" frq1="40.5" oct1="3" prs1="0.4" pow1="1.2" />
		</texture>
		<texture on="0" file="" fnorm="" scale="4.5" surf="Default" dust="0" dustS="0.2" mud="1" smoke="0" tclr="0.2 0.2 0 1" angMin="0" angMax="90" angSm="20" hMin="-300" hMax="300" hSm="20" nOn="0" noise="1" n_1="0" n2="0">
			<noise frq0="42.2" oct0="3" prs0="0.3" pow0="1.5" frq1="43.5" oct1="3" prs1="0.4" pow1="1.2" />
		</texture>
		<texture road="1" surf="roadJungle" dust="0" dustS="0.2" mud="0.2" smoke="0" tclr="0.4 0.36 0.16 0.8" />
		<par dust="Dust" mud="Mud" smoke="Smoke" />
	</terrain>
	<paged densGrass="0.2" densTrees="0.601237" grPage="100" grDist="100" grDensSmooth="1" trPage="100" trDist="100" trDistImp="800" trRdDist="5">
		<grass on="1" mtr="grass3g" clr="grClrJungle2.png" dens="0.193367" chan="0" minSx="1.18105" maxSx="1.53682" minSy="1.33784" maxSy="1.90733" swayDistr="4" swayLen="0.2" swaySpeed="0.5" />
		<grass on="1" mtr="grass18gw" clr="grClrForest2.png" dens="0.112111" chan="0" minSx="2.03793" maxSx="2.57895" minSy="1.73366" maxSy="2.281" swayDistr="4" swayLen="0.2" swaySpeed="0.5" />
		<grass on="0" mtr="grass17" clr="grClrJungle.png" dens="0.0773504" chan="0" minSx="1.96115" maxSx="2.08978" minSy="2.50147" maxSy="3.01935" swayDistr="4" swayLen="0.2" swaySpeed="0.5" />
		<grass on="1" mtr="grass16g" clr="grClrJungle.png" dens="0.1" chan="0" minSx="1.6173" maxSx="1.99746" minSy="1.8719" maxSy="2.6473" swayDistr="4" swayLen="0.2" swaySpeed="0.5" />
		<grass on="1" mtr="grass15" clr="grClrJungle.png" dens="0.0810294" chan="0" minSx="1.8194" maxSx="2.14623" minSy="1.71677" maxSy="2.14623" swayDistr="4" swayLen="0.2" swaySpeed="0.5" />
		<grass on="0" mtr="grass6g-" clr="grClrJungle.png" dens="0.264331" chan="0" minSx="1.42784" maxSx="2.05259" minSy="1.47402" maxSy="1.97926" swayDistr="4" swayLen="0.2" swaySpeed="0.5" />
		<gchan amin="0" amax="13.0997" asm="8.84039" hmin="-50" hmax="120" hsm="8" ns="0" frq="25" oct="3" prs="0.3" pow="1.2" rd="0" />
		<gchan amin="0" amax="14.7978" asm="6.32951" hmin="38.3607" hmax="84.3091" hsm="23.8691" ns="0" frq="34" oct="3" prs="0.3" pow="1.2" rd="0" />
		<gchan amin="0" amax="30" asm="20" hmin="-100" hmax="100" hsm="20" ns="0" frq="43" oct="3" prs="0.3" pow="1.2" rd="0" />
		<gchan amin="0" amax="30" asm="20" hmin="-100" hmax="100" hsm="20" ns="0" frq="52" oct="3" prs="0.3" pow="1.2" rd="0" />
		<layer on="0" name="fir05.mesh" dens="0.0499994" minScale="0.108464" maxScale="0.204664" ofsY="0" addTrRdDist="5" maxRdist="100" windFx="0.347273" windFy="0.00377026" maxTerAng="21.9118" minTerH="-100" maxTerH="100" maxDepth="0" />
		<layer on="0" name="fir14.mesh" dens="0.181998" minScale="0.0555337" maxScale="0.1942" ofsY="0" addTrRdDist="2" maxRdist="100" windFx="0.699996" windFy="0.00999462" maxTerAng="26.1929" minTerH="-100" maxTerH="110" maxDepth="0" />
		<layer on="1" name="pine1_norm.mesh" dens="0.299439" minScale="1.02513" maxScale="1.17757" ofsY="0" addTrRdDist="2" maxRdist="100" windFx="0.101235" windFy="0.00572945" maxTerAng="10.1434" minTerH="-60" maxTerH="6" maxDepth="0" />
		<layer on="1" name="pine2_tall_norm.mesh" dens="0.688154" minScale="1.07796" maxScale="1.30743" ofsY="0" addTrRdDist="1" maxRdist="6" windFx="0.0623976" windFy="0.00477668" maxTerAng="10.1434" minTerH="6.85714" maxTerH="120" maxDepth="0" />
		<layer on="1" name="pine3_fat_norm.mesh" dens="0.189539" minScale="1.06725" maxScale="1.28314" ofsY="0" addTrRdDist="1" maxRdist="100" windFx="0.0813832" windFy="0.00864708" maxTerAng="5.625" minTerH="3" maxTerH="120" maxDepth="0" />
		<layer on="0" name="treeG-17birTall.mesh" dens="0.141625" minScale="2.09301" maxScale="2.68988" ofsY="0" addTrRdDist="1" maxRdist="100" windFx="0.347273" windFy="0.0259922" maxTerAng="30.1662" minTerH="-100" maxTerH="90" maxDepth="1" />
		<layer on="1" name="fern2.mesh" dens="0.0870195" minScale="0.30276" maxScale="0.443806" ofsY="0" addTrRdDist="2" maxRdist="6" windFx="0" windFy="0" maxTerAng="29.1188" minTerH="-100" maxTerH="100" maxDepth="1" />
		<layer on="1" name="farn2.mesh" dens="0.143246" minScale="0.220067" maxScale="0.408785" ofsY="0" addTrRdDist="1" maxRdist="20" windFx="2.00128" windFy="0.0167879" maxTerAng="31.0277" minTerH="-100" maxTerH="120" maxDepth="0" />
		<layer on="0" name="" dens="0.0999996" minScale="0.0999983" maxScale="0.249999" ofsY="0" addTrRdDist="0" maxRdist="100" windFx="0" windFy="0" maxTerAng="50" minTerH="-100" maxTerH="100" maxDepth="5" />
		<layer on="0" name="" dens="0.1" minScale="0.1" maxScale="0.25" ofsY="0" addTrRdDist="0" maxRdist="100" windFx="0" windFy="0" maxTerAng="50" minTerH="-100" maxTerH="100" maxDepth="5" />
	</paged>
	<cam pos="-91.8508 49.3664 164.239" dir="0.317795 -0.250826 -0.914381" />
	<objects>
		<o name="watchtower" pos="-94.4631 -81.0043 7.53193" rot="-0.331566 -0.943432 0 0" />
		<o name="watchtower" pos="163.663 128.68 6.27634" rot="-0.647355 -0.76219 0 0" />
		<o name="big_tire" pos="67.4101 54.096 13.1797" rot="-0.000589431 0.998034 0.0572454 0.0254984" />
		<o name="big_tire" pos="71.9896 56.6301 13.5484" rot="-0.00167061 0.998334 0.057439 -0.00516673" />
		<o name="big_tire" pos="-117.678 27.5497 4.3465" rot="0.0668133 -0.104529 0.787529 0.603661" />
		<o name="big_tire" pos="-114.214 25.0839 3.94965" rot="-0.585419 0.803635 0.0609703 0.087962" />
		<o name="big_tire" pos="-109.802 23.2971 4.07229" rot="-0.0582084 0.993419 0.069357 0.0701478" />
	</objects>
</scene>
